cosmos/__init__.py
cosmos/cosmos_add_paths.py
cosmos/cosmos_configuration.py
cosmos/cosmos_delft3dfm.py
cosmos/cosmos_hurrywave.py
cosmos/cosmos_main.py
cosmos/cosmos_main_loop.py
cosmos/cosmos_meteo.py
cosmos/cosmos_model.py
cosmos/cosmos_model_loop.py
cosmos/cosmos_postprocess.py
cosmos/cosmos_scenario.py
cosmos/cosmos_sfincs.py
cosmos/cosmos_stations.py
cosmos/cosmos_tiling.py
cosmos/cosmos_timeseries.py
cosmos/cosmos_webviewer.py
cosmos/cosmos_ww3.py
cosmos/cosmos_xbeach.py
cosmos/run_cosmos.py
deltares_cosmos-0.0.10.dist-info/LICENSE
deltares_cosmos-0.0.10.dist-info/METADATA
deltares_cosmos-0.0.10.dist-info/WHEEL
deltares_cosmos-0.0.10.dist-info/top_level.txt
deltares_cosmos-0.0.10.dist-info/RECORD
