Metadata-Version: 2.1
Name: deltares-cosmos
Version: 0.0.10
Summary: Deltares CoSMoS package
Home-page: http://packages.python.org/an_example_pypi_project
Author: Maarten van Ormondt
Author-email: maarten.vanormondt@deltares.nl
License: MIT
Project-URL: Bug Tracker, https://github.com/pypa/sampleproject/issues
Keywords: cosmos
Platform: UNKNOWN
Classifier: Programming Language :: Python :: 3
Classifier: License :: OSI Approved :: MIT License
Classifier: Operating System :: OS Independent
Requires-Python: >=3.6
License-File: LICENSE
